Metadata-Version: 1.0
Name: PyFaceDet
Version: 0.2.0
Summary: See GitHub for details.
Home-page: https://github.com/zxxml/PyFace
Author: zxxml
Author-email: zxxml@outlook.com
License: UNKNOWN
Platform: UNKNOWN
